DESCRIPTION.rst
LICENSE.txt
MANIFEST.in
contributors.txt
example.py
requirements.txt
setup.cfg
setup.py
finch_urllib2/__init__.py
finch_urllib2/collection.py
finch_urllib2/errors.py
finch_urllib2/session.py
intrazon/__init__.py
intrazon/errors.py
intrazon/intrazon.py
intrazon_python.egg-info/PKG-INFO
intrazon_python.egg-info/SOURCES.txt
intrazon_python.egg-info/dependency_links.txt
intrazon_python.egg-info/requires.txt
intrazon_python.egg-info/top_level.txt