Metadata-Version: 1.1
Name: intrazon-python
Version: 0.1.2.post3
Summary: IntraZon python bindings
Home-page: https://bitbucket.org/alpenwolf/intrazon-python
Author: Markku Koponen, Alpenwolf Oy
Author-email: markku@alpenwolf.com
License: MIT
Keywords: intrazon
Platform: UNKNOWN
Classifier: Development Status :: 3 - Alpha
Classifier: Intended Audience :: Developers
Classifier: License :: OSI Approved :: MIT License
Classifier: Programming Language :: Python :: 2
Classifier: Programming Language :: Python :: 2.6
Classifier: Programming Language :: Python :: 2.7
Classifier: Programming Language :: Python :: 3
Classifier: Programming Language :: Python :: 3.2
Classifier: Programming Language :: Python :: 3.3
Classifier: Programming Language :: Python :: 3.4
